Metadata-Version: 1.0
Name: shoppingCart
Version: 1.3.0
Summary: shoppingCart is a open source cart developed using Python language to manage cart in Ecommerce applications.
Home-page: http://bitbucket.org/dharmeshpatel/shoppingcart
Author: Dharmesh Patel
Author-email: mr[dot]dlpatel[at]gmail[dot]com
License: BSD
Keywords: cart  shopcart shoppingcart e-shop e-shopcart e-shoppingCart
Platform: any
Classifier: Development Status :: 5 - Production/Stable
Classifier: License :: OSI Approved :: BSD License
Classifier: Programming Language :: Python
